<?xml version="1.0" encoding="utf-8"?>
<extension version="3.5" type="plugin" group="system" method="upgrade" >
        <name>Gurucan User Register</name>
        <creationDate>May 2021</creationDate>
		<author>LSPL</author>
		<authorEmail>info@laitmatus.com</authorEmail>
		<authorUrl>https://laitmatus.com/</authorUrl>
		<copyright>LSPL 2021</copyright>
		<license>GPL2 - General Public License, Version 2</license>
		<version>1.0.0</version>
		<description>Register user in joomla when someone register in Gurucan</description>
		<files>
                <filename plugin="gurucan_register">gurucan_register.php</filename>
                <filename>index.html</filename>
        </files>
		<config>
		</config>
</extension>